Metadata-Version: 1.1
Name: shellish
Version: 5
Summary: A framework for CLI/shell programs.
Home-page: https://github.com/mayfield/shellish/
Author: Justin Mayfield
Author-email: tooker@gmail.com
License: MIT
Platform: UNKNOWN
Classifier: Development Status :: 4 - Beta
Classifier: Intended Audience :: Developers
Classifier: License :: OSI Approved :: MIT License
Classifier: Operating System :: OS Independent
Classifier: Programming Language :: Python
Classifier: Programming Language :: Python :: 3.5
Classifier: Programming Language :: Python :: 3.6
Classifier: Topic :: Software Development :: Libraries
Classifier: Topic :: System :: Shells
